{"_default": {"1": {"user_id": 6177562485, "username": "mdvcc", "chat_id": 6177562485}, "2": {"user_id": 6542924049, "username": "ibnuumid", "chat_id": 6542924049}, "3": {"user_id": 412726202, "username": "Mr_programmer96", "chat_id": 412726202}, "4": {"user_id": 206919715, "username": "oppoxonov", "chat_id": 206919715}, "5": {"user_id": 7152079156, "username": "Tohir560", "chat_id": 7152079156}, "6": {"user_id": 457333215, "username": "shenazarov85", "chat_id": 457333215}, "7": {"user_id": 6601529100, "username": "null", "chat_id": 6601529100}, "8": {"user_id": 800523235, "username": "null", "chat_id": 800523235}, "9": {"user_id": 1525253278, "username": "null", "chat_id": 1525253278}, "10": {"user_id": 933914837, "username": "seulgibearrr", "chat_id": 933914837}, "11": {"user_id": 6044455046, "username": "null", "chat_id": 6044455046}, "12": {"user_id": 6987426065, "username": "null", "chat_id": 6987426065}, "13": {"user_id": 6653040888, "username": "null", "chat_id": 6653040888}, "14": {"user_id": 6751660668, "username": "null", "chat_id": 6751660668}, "15": {"user_id": 1462497605, "username": "null", "chat_id": 1462497605}, "16": {"user_id": 7175218100, "username": "null", "chat_id": 7175218100}, "17": {"user_id": 6758778008, "username": "null", "chat_id": 6758778008}, "18": {"user_id": 6466532862, "username": "null", "chat_id": 6466532862}, "19": {"user_id": 7024560854, "username": "null", "chat_id": 7024560854}, "20": {"user_id": 22998560, "username": "Abror0049", "chat_id": 22998560}, "21": {"user_id": 6902472354, "username": "null", "chat_id": 6902472354}, "22": {"user_id": 6587888227, "username": "null", "chat_id": 6587888227}, "23": {"user_id": 1824729264, "username": "null", "chat_id": 1824729264}, "24": {"user_id": 5692802103, "username": "Rufina_0007", "chat_id": 5692802103}, "25": {"user_id": 6286797756, "username": "Cmaybech", "chat_id": 6286797756}, "26": {"user_id": 888556729, "username": "null", "chat_id": 888556729}, "27": {"user_id": 963206116, "username": "Xudoberdi59", "chat_id": 963206116}, "28": {"user_id": 610818763, "username": "null", "chat_id": 610818763}, "29": {"user_id": 7174240611, "username": "null", "chat_id": 7174240611}, "30": {"user_id": 774186155, "username": "daleka9405", "chat_id": 774186155}, "31": {"user_id": 6715273519, "username": "null", "chat_id": 6715273519}, "32": {"user_id": 6552629395, "username": "username_Sardor", "chat_id": 6552629395}, "33": {"user_id": 667523648, "username": "Bek_1310", "chat_id": 667523648}, "34": {"user_id": 5689574191, "username": "null", "chat_id": 5689574191}, "35": {"user_id": 1364494178, "username": "Is1am_202", "chat_id": 1364494178}, "36": {"user_id": 750578656, "username": "null", "chat_id": 750578656}, "37": {"user_id": 830768773, "username": "mirzaraxmon", "chat_id": 830768773}, "38": {"user_id": 2041330442, "username": "Akhmad_off", "chat_id": 2041330442}, "39": {"user_id": 446807525, "username": "null", "chat_id": 446807525}, "40": {"user_id": 5010735951, "username": "Nurullo077", "chat_id": 5010735951}, "41": {"user_id": 3768958, "username": "ZedRedDev", "chat_id": 3768958}, "42": {"user_id": 435261666, "username": "null", "chat_id": 435261666}, "43": {"user_id": 2045672089, "username": "Ilhom_423", "chat_id": 2045672089}, "44": {"user_id": 462067840, "username": "NanuAchildiyeva", "chat_id": 462067840}, "45": {"user_id": 5606861750, "username": "Shavonamebell", "chat_id": 5606861750}, "46": {"user_id": 6007223630, "username": "Ibroximovelyorbek91196", "chat_id": 6007223630}, "47": {"user_id": 1081529677, "username": "jakhongir6", "chat_id": 1081529677}, "48": {"user_id": 1165526712, "username": "hoshimoff_888", "chat_id": 1165526712}, "49": {"user_id": 802856323, "username": "Tillo119", "chat_id": 802856323}, "50": {"user_id": 7033413718, "username": "Mitti_qalbb", "chat_id": 7033413718}, "51": {"user_id": 58590733, "username": "Dostonoo9", "chat_id": 58590733}, "52": {"user_id": 5188626413, "username": "akhmedov4407", "chat_id": 5188626413}, "53": {"user_id": 1151187321, "username": "null", "chat_id": 1151187321}, "54": {"user_id": 7008018081, "username": "Suppermen_2024", "chat_id": 7008018081}, "55": {"user_id": 6631268154, "username": "sStudent0425", "chat_id": 6631268154}, "56": {"user_id": 853470101, "username": "sszuxa", "chat_id": 853470101}, "57": {"user_id": 1172109869, "username": "ANJJAGM6680", "chat_id": 1172109869}, "58": {"user_id": 864753053, "username": "Musulmon26", "chat_id": 864753053}, "59": {"user_id": 6006694953, "username": "null", "chat_id": 6006694953}, "60": {"user_id": 7060994656, "username": "null", "chat_id": 7060994656}, "61": {"user_id": 1385750394, "username": "Bolakay7979", "chat_id": 1385750394}, "62": {"user_id": 379742113, "username": "null", "chat_id": 379742113}, "63": {"user_id": 749729727, "username": "yakubjonov_94", "chat_id": 749729727}, "64": {"user_id": 1632497055, "username": "Muhammadyusuf_234", "chat_id": 1632497055}, "65": {"user_id": 5914792485, "username": "ds_Zalatoy", "chat_id": 5914792485}, "66": {"user_id": 820200001, "username": "Diyorbek_5330", "chat_id": 820200001}, "67": {"user_id": 660685124, "username": "null", "chat_id": 660685124}, "68": {"user_id": 915050030, "username": "nuralimaxmudov_701", "chat_id": 915050030}, "69": {"user_id": 5671576033, "username": "null", "chat_id": 5671576033}, "70": {"user_id": 1627859203, "username": "MAMADAMINOV_2002", "chat_id": 1627859203}, "71": {"user_id": 6100704276, "username": "e_one_finance_003", "chat_id": 6100704276}, "72": {"user_id": 1452751179, "username": "doston_9191", "chat_id": 1452751179}, "73": {"user_id": 6788799579, "username": "Nasriddinov_700", "chat_id": 6788799579}, "74": {"user_id": 6878528734, "username": "null", "chat_id": 6878528734}, "75": {"user_id": 5487709922, "username": "null", "chat_id": 5487709922}, "76": {"user_id": 1264992409, "username": "ilhomov_12", "chat_id": 1264992409}, "77": {"user_id": 6257771729, "username": "nusratillo_ibrokhimov_002", "chat_id": 6257771729}, "78": {"user_id": 952637981, "username": "null", "chat_id": 952637981}}}